{
  "entity": "minecraft:zombie",
  "name": "精锐僵尸剑士",
  "visualscale": 1.2,
  "experience": 500,
  "effects": {},
  "attributes": {
    "generic.max_health": 2000,
    "generic.follow_range": 24,
    "generic.knockback_resistance": 2,
    "generic.attack_damage": 10
  },
  "customattributes": {
  },
  "gear": {
    "mainhand": "{id: \"magistuarmory:noble_sword\", Count: 1b, tag: {Damage: 0}}",
    "helmet": "{id: \"magistuarmory:rustedchainmail_helmet\", Count: 1b, tag: {Damage: 0}}",
    "chestplate": "{id: \"magistuarmory:rustedchainmail_chestplate\", Count: 1b, tag: {Damage: 0}}",
    "leggings": "{id: \"magistuarmory:rustedchainmail_leggings\", Count: 1b, tag: {Damage: 0}}",
    "feet": "{id: \"magistuarmory:rustedchainmail_boots\", Count: 1b, tag: {Damage: 0}}"
  },
  "ai-goals": {
    "brutalbosses:aftercombatregen": {
      "amount": 1
    },
    "brutalbosses:jumpattack": {
      "attackdist": 4,
      "extraDamage": 8,
      "maxdist": 30,
      "mindist": 10,
      "maxheight": 20,
      "duration": 50,
      "interval": 100
    },
    "brutalbosses:charge": {
      "mindist": 1,
      "duration": 4,
      "interval": 20
    }
  },
  "spawnatchest": {}
}